krishna_stt/__init__.py
krishna_stt-0.1.dist-info/METADATA
krishna_stt-0.1.dist-info/WHEEL
krishna_stt-0.1.dist-info/top_level.txt
krishna_stt-0.1.dist-info/RECORD
