Metadata-Version: 2.1
Name: krishna_stt
Version: 0.1
Summary: This is a speech to text package created by Krishna Lodhi
Author: Krishna Lodhi
Author-email: krish9lodhi2004@gmail.com
